{
  "info": {
    "_postman_id": "55885cef-8a3d-4882-a98e-ab14ad7e322d",
    "name": "CRA API - Complete Tests",
    "description": "Collection complete des endpoints CRA.\n\nPre-requis importants:\n1) Connecte-toi d'abord avec 'Login Admin' pour remplir {{admin_token}} automatiquement.\n2) Les endpoints /api/cra/** exigent un token ROLE_COLLABORATEUR ({{collaborateur_token}}).\n3) Regle metier: la saisie CRA (remplir/update/soumettre) est autorisee uniquement dans la fenetre de declaration configuree cote backend (timezone Europe/Paris), sauf cas REJECTED.\n4) Lors de la creation d'un collaborateur, renseigne {{collaborateur_password}}: ce mot de passe pourra ensuite etre utilise pour le login collaborateur.",
    "schema": "https://schema.getpostman.com/json/collection/v2.1.0/collection.json"
  },
  "item": [
    {
      "name": "00 - Auth",
      "item": [
        {
          "name": "Login Admin",
          "event": [
            {
              "listen": "test",
              "script": {
                "type": "text/javascript",
                "exec": [
                  "pm.test('Status 200', function () { pm.response.to.have.status(200); });",
                  "let data = {};",
                  "try { data = pm.response.json(); } catch (e) {}",
                  "if (data.token) { pm.environment.set('admin_token', data.token); }",
                  "if (data.role) { pm.environment.set('admin_role', data.role); }"
                ]
              }
            }
          ],
          "request": {
            "method": "POST",
            "header": [
              {
                "key": "Content-Type",
                "value": "application/json"
              }
            ],
            "body": {
              "mode": "raw",
              "raw": "{\n  \"email\": \"{{admin_email}}\",\n  \"password\": \"{{admin_password}}\"\n}",
              "options": {
                "raw": {
                  "language": "json"
                }
              }
            },
            "url": "{{baseUrl}}/api/auth/login",
            "description": "Recupere et stocke automatiquement {{admin_token}}."
          },
          "response": []
        },
        {
          "name": "Login Collaborateur",
          "event": [
            {
              "listen": "test",
              "script": {
                "type": "text/javascript",
                "exec": [
                  "let data = {};",
                  "try { data = pm.response.json(); } catch (e) {}",
                  "if (data.token) { pm.environment.set('collaborateur_token', data.token); }",
                  "if (data.role) { pm.environment.set('collaborateur_role', data.role); }"
                ]
              }
            }
          ],
          "request": {
            "method": "POST",
            "header": [
              {
                "key": "Content-Type",
                "value": "application/json"
              }
            ],
            "body": {
              "mode": "raw",
              "raw": "{\n  \"email\": \"{{collaborateur_email}}\",\n  \"password\": \"{{collaborateur_password}}\"\n}",
              "options": {
                "raw": {
                  "language": "json"
                }
              }
            },
            "url": "{{baseUrl}}/api/auth/login",
            "description": "Recupere et stocke automatiquement {{collaborateur_token}}."
          },
          "response": []
        },
        {
          "name": "Logout Admin",
          "event": [
            {
              "listen": "test",
              "script": {
                "type": "text/javascript",
                "exec": [
                  "pm.test('Status 200', function () { pm.response.to.have.status(200); });",
                  "let data = {};",
                  "try { data = pm.response.json(); } catch (e) {}",
                  "pm.test('Payload contient message', function () { pm.expect(data).to.have.property('message'); });",
                  "pm.environment.unset('admin_token');",
                  "pm.environment.unset('admin_role');"
                ]
              }
            }
          ],
          "request": {
            "method": "POST",
            "header": [
              {
                "key": "Authorization",
                "value": "Bearer {{admin_token}}"
              }
            ],
            "url": "{{baseUrl}}/api/auth/logout",
            "description": "Invalide le token admin courant puis nettoie les variables d'environnement."
          },
          "response": []
        },
        {
          "name": "Logout Collaborateur",
          "event": [
            {
              "listen": "test",
              "script": {
                "type": "text/javascript",
                "exec": [
                  "pm.test('Status 200', function () { pm.response.to.have.status(200); });",
                  "let data = {};",
                  "try { data = pm.response.json(); } catch (e) {}",
                  "pm.test('Payload contient message', function () { pm.expect(data).to.have.property('message'); });",
                  "pm.environment.unset('collaborateur_token');",
                  "pm.environment.unset('collaborateur_role');"
                ]
              }
            }
          ],
          "request": {
            "method": "POST",
            "header": [
              {
                "key": "Authorization",
                "value": "Bearer {{collaborateur_token}}"
              }
            ],
            "url": "{{baseUrl}}/api/auth/logout",
            "description": "Invalide le token collaborateur courant puis nettoie les variables d'environnement."
          },
          "response": []
        }
      ]
    },
    {
      "name": "10 - Admin / Collaborateurs",
      "item": [
        {
          "name": "Lister Collaborateurs",
          "request": {
            "method": "GET",
            "header": [
              {
                "key": "Authorization",
                "value": "Bearer {{admin_token}}"
              }
            ],
            "url": "{{baseUrl}}/api/collaborateurs"
          },
          "response": []
        },
        {
          "name": "Creer Collaborateur",
          "event": [
            {
              "listen": "prerequest",
              "script": {
                "type": "text/javascript",
                "exec": [
                  "pm.environment.set('collaborateur_email', 'collab.' + Date.now() + '@cbx.com');",
                  "if (!pm.environment.get('collaborateur_password')) {",
                  "  pm.environment.set('collaborateur_password', 'Collab123!');",
                  "}"
                ]
              }
            },
            {
              "listen": "test",
              "script": {
                "type": "text/javascript",
                "exec": [
                  "pm.test('Status 201', function () { pm.response.to.have.status(201); });",
                  "let data = {};",
                  "try { data = pm.response.json(); } catch (e) {}",
                  "if (data.id) { pm.environment.set('collaborateur_id', String(data.id)); }",
                  "if (data.email) { pm.environment.set('collaborateur_email', data.email); }"
                ]
              }
            }
          ],
          "request": {
            "method": "POST",
            "header": [
              {
                "key": "Authorization",
                "value": "Bearer {{admin_token}}"
              },
              {
                "key": "Content-Type",
                "value": "application/json"
              }
            ],
            "body": {
              "mode": "raw",
              "raw": "{\n  \"nom\": \"Dupont\",\n  \"prenom\": \"Jean\",\n  \"email\": \"{{collaborateur_email}}\",\n  \"password\": \"{{collaborateur_password}}\",\n  \"contrat\": \"CDI\",\n  \"seniorite\": \"JUNIOR\",\n  \"salaire\": \"35000\"\n}",
              "options": {
                "raw": {
                  "language": "json"
                }
              }
            },
            "url": "{{baseUrl}}/api/collaborateurs"
          },
          "response": []
        },
        {
          "name": "Get Collaborateur By Id",
          "request": {
            "method": "GET",
            "header": [
              {
                "key": "Authorization",
                "value": "Bearer {{admin_token}}"
              }
            ],
            "url": "{{baseUrl}}/api/collaborateurs/{{collaborateur_id}}"
          },
          "response": []
        },
        {
          "name": "Update Collaborateur",
          "request": {
            "method": "PUT",
            "header": [
              {
                "key": "Authorization",
                "value": "Bearer {{admin_token}}"
              },
              {
                "key": "Content-Type",
                "value": "application/json"
              }
            ],
            "body": {
              "mode": "raw",
              "raw": "{\n  \"nom\": \"Dupont\",\n  \"prenom\": \"Jeanne\",\n  \"email\": \"{{collaborateur_email}}\",\n  \"contrat\": \"PORTAGE\",\n  \"seniorite\": \"CONFIRME\",\n  \"salaire\": \"42000\"\n}",
              "options": {
                "raw": {
                  "language": "json"
                }
              }
            },
            "url": "{{baseUrl}}/api/collaborateurs/{{collaborateur_id}}"
          },
          "response": []
        },
        {
          "name": "Toggle Activation Collaborateur",
          "event": [
            {
              "listen": "test",
              "script": {
                "type": "text/javascript",
                "exec": [
                  "pm.test('Status 200', function () { pm.response.to.have.status(200); });",
                  "let data = {};",
                  "try { data = pm.response.json(); } catch (e) {}",
                  "pm.test('Payload contient actif', function () { pm.expect(data).to.have.property('actif'); });"
                ]
              }
            }
          ],
          "request": {
            "method": "PATCH",
            "header": [
              {
                "key": "Authorization",
                "value": "Bearer {{admin_token}}"
              }
            ],
            "url": "{{baseUrl}}/api/collaborateurs/{{collaborateur_id}}/activation"
          },
          "response": []
        }
      ]
    },
    {
      "name": "20 - Admin / Missions",
      "item": [
        {
          "name": "Lister Missions",
          "request": {
            "method": "GET",
            "header": [
              {
                "key": "Authorization",
                "value": "Bearer {{admin_token}}"
              }
            ],
            "url": "{{baseUrl}}/api/missions"
          },
          "response": []
        },
        {
          "name": "Creer Mission",
          "event": [
            {
              "listen": "test",
              "script": {
                "type": "text/javascript",
                "exec": [
                  "pm.test('Status 201', function () { pm.response.to.have.status(201); });",
                  "let data = {};",
                  "try { data = pm.response.json(); } catch (e) {}",
                  "if (data.id) { pm.environment.set('mission_id', String(data.id)); }"
                ]
              }
            }
          ],
          "request": {
            "method": "POST",
            "header": [
              {
                "key": "Authorization",
                "value": "Bearer {{admin_token}}"
              },
              {
                "key": "Content-Type",
                "value": "application/json"
              }
            ],
            "body": {
              "mode": "raw",
              "raw": "{\n  \"titre\": \"Mission Client A\",\n  \"description\": \"Developpement et support\",\n  \"motif\": \"Renfort equipe\",\n  \"dateDebut\": \"2026-03-01\",\n  \"dateFin\": \"2026-12-31\",\n  \"tjm\": 550\n}",
              "options": {
                "raw": {
                  "language": "json"
                }
              }
            },
            "url": "{{baseUrl}}/api/missions"
          },
          "response": []
        },
        {
          "name": "Get Mission By Id",
          "request": {
            "method": "GET",
            "header": [
              {
                "key": "Authorization",
                "value": "Bearer {{admin_token}}"
              }
            ],
            "url": "{{baseUrl}}/api/missions/{{mission_id}}"
          },
          "response": []
        },
        {
          "name": "Update Mission",
          "request": {
            "method": "PUT",
            "header": [
              {
                "key": "Authorization",
                "value": "Bearer {{admin_token}}"
              },
              {
                "key": "Content-Type",
                "value": "application/json"
              }
            ],
            "body": {
              "mode": "raw",
              "raw": "{\n  \"titre\": \"Mission Client A - Update\",\n  \"description\": \"Developpement, support et run\",\n  \"motif\": \"Extension\",\n  \"dateDebut\": \"2026-03-01\",\n  \"dateFin\": \"2026-12-31\",\n  \"tjm\": 600\n}",
              "options": {
                "raw": {
                  "language": "json"
                }
              }
            },
            "url": "{{baseUrl}}/api/missions/{{mission_id}}"
          },
          "response": []
        },
        {
          "name": "Affecter Mission a Collaborateur",
          "event": [
            {
              "listen": "test",
              "script": {
                "type": "text/javascript",
                "exec": [
                  "pm.test('Status 201', function () { pm.response.to.have.status(201); });",
                  "let data = {};",
                  "try { data = pm.response.json(); } catch (e) {}",
                  "if (data.id) { pm.environment.set('assignment_id', String(data.id)); }"
                ]
              }
            }
          ],
          "request": {
            "method": "POST",
            "header": [
              {
                "key": "Authorization",
                "value": "Bearer {{admin_token}}"
              },
              {
                "key": "Content-Type",
                "value": "application/json"
              }
            ],
            "body": {
              "mode": "raw",
              "raw": "{\n  \"collaborateurId\": {{collaborateur_id}},\n  \"missionId\": {{mission_id}},\n  \"dateDebut\": \"2026-03-01\",\n  \"dateFin\": \"2026-12-31\"\n}",
              "options": {
                "raw": {
                  "language": "json"
                }
              }
            },
            "url": "{{baseUrl}}/api/missions/assign"
          },
          "response": []
        },
        {
          "name": "Supprimer Mission",
          "event": [
            {
              "listen": "test",
              "script": {
                "type": "text/javascript",
                "exec": [
                  "pm.test('Status 200', function () { pm.response.to.have.status(200); });",
                  "let data = {};",
                  "try { data = pm.response.json(); } catch (e) {}",
                  "pm.test('Payload contient message', function () { pm.expect(data).to.have.property('message'); });",
                  "pm.environment.unset('mission_id');"
                ]
              }
            }
          ],
          "request": {
            "method": "DELETE",
            "header": [
              {
                "key": "Authorization",
                "value": "Bearer {{admin_token}}"
              }
            ],
            "url": "{{baseUrl}}/api/missions/{{mission_id}}",
            "description": "A executer en dernier si tu veux nettoyer les donnees de test."
          },
          "response": []
        }
      ]
    },
    {
      "name": "30 - CRA Collaborateur (ROLE_COLLABORATEUR)",
      "item": [
        {
          "name": "Get Mon CRA (mois/annee)",
          "event": [
            {
              "listen": "test",
              "script": {
                "type": "text/javascript",
                "exec": [
                  "let data = {};",
                  "try { data = pm.response.json(); } catch (e) {}",
                  "if (data.id) { pm.environment.set('cra_id', String(data.id)); }"
                ]
              }
            }
          ],
          "request": {
            "method": "GET",
            "header": [
              {
                "key": "Authorization",
                "value": "Bearer {{collaborateur_token}}"
              }
            ],
            "url": "{{baseUrl}}/api/cra?mois={{mois}}&annee={{annee}}"
          },
          "response": []
        },
        {
          "name": "Get Mes CRAs",
          "request": {
            "method": "GET",
            "header": [
              {
                "key": "Authorization",
                "value": "Bearer {{collaborateur_token}}"
              }
            ],
            "url": "{{baseUrl}}/api/cra/mes-cras"
          },
          "response": []
        },
        {
          "name": "Remplir Mois",
          "request": {
            "method": "PUT",
            "header": [
              {
                "key": "Authorization",
                "value": "Bearer {{collaborateur_token}}"
              }
            ],
            "url": "{{baseUrl}}/api/cra/{{cra_id}}/remplir-mois",
            "description": "Aucun body. Remplit les jours ouvres en TRAVAILLE=1.0. Possible uniquement dans la fenetre de declaration configuree cote backend (sauf statut REJECTED)."
          },
          "response": []
        },
        {
          "name": "Update Jour CRA (TRAVAILLE)",
          "request": {
            "method": "PUT",
            "header": [
              {
                "key": "Authorization",
                "value": "Bearer {{collaborateur_token}}"
              },
              {
                "key": "Content-Type",
                "value": "application/json"
              }
            ],
            "body": {
              "mode": "raw",
              "raw": "{\n  \"date\": \"{{jour_date}}\",\n  \"type\": \"TRAVAILLE\",\n  \"valeur\": 1.0\n}",
              "options": {
                "raw": {
                  "language": "json"
                }
              }
            },
            "url": "{{baseUrl}}/api/cra/{{cra_id}}/jour"
          },
          "response": []
        },
        {
          "name": "Update Jour CRA (CONGE)",
          "request": {
            "method": "PUT",
            "header": [
              {
                "key": "Authorization",
                "value": "Bearer {{collaborateur_token}}"
              },
              {
                "key": "Content-Type",
                "value": "application/json"
              }
            ],
            "body": {
              "mode": "raw",
              "raw": "{\n  \"date\": \"{{jour_absence_date}}\",\n  \"type\": \"CONGE\",\n  \"valeur\": 1.0\n}",
              "options": {
                "raw": {
                  "language": "json"
                }
              }
            },
            "url": "{{baseUrl}}/api/cra/{{cra_id}}/jour"
          },
          "response": []
        },
        {
          "name": "Soumettre CRA",
          "request": {
            "method": "POST",
            "header": [
              {
                "key": "Authorization",
                "value": "Bearer {{collaborateur_token}}"
              }
            ],
            "url": "{{baseUrl}}/api/cra/{{cra_id}}/soumettre"
          },
          "response": []
        }
      ]
    },
    {
      "name": "35 - Absences",
      "item": [
        {
          "name": "Mes absences (Collaborateur)",
          "event": [
            {
              "listen": "test",
              "script": {
                "type": "text/javascript",
                "exec": [
                  "pm.test('Status 200', function () { pm.response.to.have.status(200); });",
                  "let data = {};",
                  "try { data = pm.response.json(); } catch (e) {}",
                  "pm.test('Payload contient annee', function () { pm.expect(data).to.have.property('annee'); });",
                  "pm.test('Payload contient absences', function () { pm.expect(data).to.have.property('absences'); });"
                ]
              }
            }
          ],
          "request": {
            "method": "GET",
            "header": [
              {
                "key": "Authorization",
                "value": "Bearer {{collaborateur_token}}"
              }
            ],
            "url": "{{baseUrl}}/api/cra/mes-absences?annee={{annee}}"
          },
          "response": []
        },
        {
          "name": "Absences collaborateur (Admin)",
          "event": [
            {
              "listen": "test",
              "script": {
                "type": "text/javascript",
                "exec": [
                  "pm.test('Status 200', function () { pm.response.to.have.status(200); });",
                  "let data = {};",
                  "try { data = pm.response.json(); } catch (e) {}",
                  "pm.test('Payload contient collaborateurId', function () { pm.expect(data).to.have.property('collaborateurId'); });",
                  "pm.test('Payload contient totalJours', function () { pm.expect(data).to.have.property('totalJours'); });"
                ]
              }
            }
          ],
          "request": {
            "method": "GET",
            "header": [
              {
                "key": "Authorization",
                "value": "Bearer {{admin_token}}"
              }
            ],
            "url": "{{baseUrl}}/api/admin/collaborateurs/{{collaborateur_id}}/absences?annee={{annee}}"
          },
          "response": []
        }
      ]
    },
    {
      "name": "40 - CRA Admin Validation",
      "item": [
        {
          "name": "Lister CRAs a valider",
          "request": {
            "method": "GET",
            "header": [
              {
                "key": "Authorization",
                "value": "Bearer {{admin_token}}"
              }
            ],
            "url": "{{baseUrl}}/api/admin/cra/a-valider"
          },
          "response": []
        },
        {
          "name": "Lister tous les CRAs",
          "request": {
            "method": "GET",
            "header": [
              {
                "key": "Authorization",
                "value": "Bearer {{admin_token}}"
              }
            ],
            "url": "{{baseUrl}}/api/admin/cra"
          },
          "response": []
        },
        {
          "name": "Approuver CRA",
          "request": {
            "method": "POST",
            "header": [
              {
                "key": "Authorization",
                "value": "Bearer {{admin_token}}"
              }
            ],
            "url": "{{baseUrl}}/api/admin/cra/{{cra_id}}/approuver",
            "description": "Necessite un CRA en statut SUBMITTED."
          },
          "response": []
        },
        {
          "name": "Rejeter CRA",
          "request": {
            "method": "POST",
            "header": [
              {
                "key": "Authorization",
                "value": "Bearer {{admin_token}}"
              },
              {
                "key": "Content-Type",
                "value": "application/json"
              }
            ],
            "body": {
              "mode": "raw",
              "raw": "{\n  \"motif\": \"Justificatifs incomplets\"\n}",
              "options": {
                "raw": {
                  "language": "json"
                }
              }
            },
            "url": "{{baseUrl}}/api/admin/cra/{{cra_id}}/rejeter",
            "description": "Necessite un CRA en statut SUBMITTED."
          },
          "response": []
        },
        {
          "name": "Invalider CRA",
          "request": {
            "method": "POST",
            "header": [
              {
                "key": "Authorization",
                "value": "Bearer {{admin_token}}"
              },
              {
                "key": "Content-Type",
                "value": "application/json"
              }
            ],
            "body": {
              "mode": "raw",
              "raw": "{\n  \"motif\": \"Correction demandee\"\n}",
              "options": {
                "raw": {
                  "language": "json"
                }
              }
            },
            "url": "{{baseUrl}}/api/admin/cra/{{cra_id}}/invalider",
            "description": "Necessite un CRA en statut APPROVED."
          },
          "response": []
        }
      ]
    }
  ],
  "variable": [
    {
      "key": "baseUrl",
      "value": "http://localhost:8080"
    },
    {
      "key": "admin_email",
      "value": "admin@cbx.com"
    },
    {
      "key": "admin_password",
      "value": "admin123"
    },
    {
      "key": "admin_token",
      "value": ""
    },
    {
      "key": "admin_role",
      "value": ""
    },
    {
      "key": "collaborateur_email",
      "value": "collab.test@cbx.com"
    },
    {
      "key": "collaborateur_password",
      "value": "Collab123!"
    },
    {
      "key": "collaborateur_token",
      "value": ""
    },
    {
      "key": "collaborateur_role",
      "value": ""
    },
    {
      "key": "collaborateur_id",
      "value": ""
    },
    {
      "key": "mission_id",
      "value": ""
    },
    {
      "key": "assignment_id",
      "value": ""
    },
    {
      "key": "cra_id",
      "value": ""
    },
    {
      "key": "mois",
      "value": "3"
    },
    {
      "key": "annee",
      "value": "2026"
    },
    {
      "key": "jour_date",
      "value": "2026-03-24"
    },
    {
      "key": "jour_absence_date",
      "value": "2026-03-25"
    }
  ]
}
